robotdatapy/__init__.py
robotdatapy/camera.py
robotdatapy/data_fusion.py
robotdatapy/exceptions.py
robotdatapy/geometry.py
robotdatapy/ros_msg_convert.py
robotdatapy/transform.py
robotdatapy/data/__init__.py
robotdatapy/data/array_data.py
robotdatapy/data/general_data.py
robotdatapy/data/gps_data.py
robotdatapy/data/img_data.py
robotdatapy/data/pointcloud_data.py
robotdatapy/data/pose_data.py
robotdatapy/data/robot_data.py
robotdatapy/data/tmp.py
robotdatapy-1.1.4.dist-info/LICENSE
robotdatapy-1.1.4.dist-info/METADATA
robotdatapy-1.1.4.dist-info/WHEEL
robotdatapy-1.1.4.dist-info/top_level.txt
robotdatapy-1.1.4.dist-info/RECORD
