Metadata-Version: 2.1
Name: robotdatapy
Version: 1.1.4
Summary: Python package for interfacing with robot data
Home-page: https://github.com/mbpeterson70/robotdatapy
Author: Mason Peterson
Author-email: masonbp@mit.edu
License: MIT
License-File: LICENSE
Requires-Dist: evo
Requires-Dist: gtsam
Requires-Dist: numpy
Requires-Dist: opencv-python
Requires-Dist: pandas
Requires-Dist: pykitti
Requires-Dist: rosbags
Requires-Dist: rosbags-image
Requires-Dist: scipy
Requires-Dist: utm
